idtrackerai_app/__init__.py
idtrackerai_app/__main__.py
idtrackerai_app/base_idtrackerai.py
idtrackerai_app/helpers.py
idtrackerai_app/win_idtrackerai.py
idtrackerai_app/gui/__init__.py
idtrackerai_app/gui/grapharea_win.py
idtrackerai_app/gui/range_win.py
idtrackerai_app/gui/roi_selection.py
pyforms-gui/__init__.py
pyforms-gui/setup.py
pyforms-gui/pyforms/__init__.py
pyforms-gui/pyforms/basewidget.py
pyforms-gui/pyforms/controls.py
pyforms-gui/pyforms/dialogs.py
pyforms-gui/pyforms/settings.py
pyforms-gui/pyforms_gui/__init__.py
pyforms-gui/pyforms_gui/allcontrols.py
pyforms-gui/pyforms_gui/appmanager.py
pyforms-gui/pyforms_gui/basewidget.py
pyforms-gui/pyforms_gui/organizers.py
pyforms-gui/pyforms_gui/resources_settings.py
pyforms-gui/pyforms_gui/settings.py
pyforms-gui/pyforms_gui/controls/__init__.py
pyforms-gui/pyforms_gui/controls/control_base.py
pyforms-gui/pyforms_gui/controls/control_boundingslider.py
pyforms-gui/pyforms_gui/controls/control_button.py
pyforms-gui/pyforms_gui/controls/control_checkbox.py
pyforms-gui/pyforms_gui/controls/control_checkboxlist.py
pyforms-gui/pyforms_gui/controls/control_codeeditor.py
pyforms-gui/pyforms_gui/controls/control_combo.py
pyforms-gui/pyforms_gui/controls/control_dir.py
pyforms-gui/pyforms_gui/controls/control_dockwidget.py
pyforms-gui/pyforms_gui/controls/control_emptywidget.py
pyforms-gui/pyforms_gui/controls/control_file.py
pyforms-gui/pyforms_gui/controls/control_filestree.py
pyforms-gui/pyforms_gui/controls/control_image.py
pyforms-gui/pyforms_gui/controls/control_label.py
pyforms-gui/pyforms_gui/controls/control_list.py
pyforms-gui/pyforms_gui/controls/control_matplotlib.py
pyforms-gui/pyforms_gui/controls/control_mdiarea.py
pyforms-gui/pyforms_gui/controls/control_number.py
pyforms-gui/pyforms_gui/controls/control_opengl.py
pyforms-gui/pyforms_gui/controls/control_password.py
pyforms-gui/pyforms_gui/controls/control_progress.py
pyforms-gui/pyforms_gui/controls/control_slider.py
idtrackerai_app-0.0.13.dist-info/METADATA
idtrackerai_app-0.0.13.dist-info/WHEEL
idtrackerai_app-0.0.13.dist-info/entry_points.txt
idtrackerai_app-0.0.13.dist-info/top_level.txt
idtrackerai_app-0.0.13.dist-info/RECORD
